MySQLWrapperPackage/__init__.py
MySQLWrapperPackage/connections.py
MySQLWrapperPackage/mysqlquerries.py
MySQLWrapperPackage/wrapper.py
MySQLWrapperPackage/wrapperabstraction.py
mysqlwrapperpackage-0.1.dist-info/LICENCE
mysqlwrapperpackage-0.1.dist-info/METADATA
mysqlwrapperpackage-0.1.dist-info/WHEEL
mysqlwrapperpackage-0.1.dist-info/top_level.txt
mysqlwrapperpackage-0.1.dist-info/RECORD
