Metadata-Version: 2.1
Name: mysqlwrapperpackage
Version: 0.1
Summary: MySQL Python Wrapper Package
Home-page: https://github.com/Sharonsyra/MySQLWrapperPackage
Author: Flying Circus
Author-email: sharonwaithii@gmail.com
License: MIT
Platform: UNKNOWN
